telegramlangtags/__init__.py
telegramlangtags/enums.py
telegramlangtags-1.0.0.dist-info/METADATA
telegramlangtags-1.0.0.dist-info/WHEEL
telegramlangtags-1.0.0.dist-info/RECORD
