Metadata-Version: 2.1
Name: telegramlangtags
Version: 1.0.0
Summary: Telegram language codes by IETF language tag ISO-639-1
License: GNU
Author: yeghorkikhai
Author-email: yeghorkikhai@gmail.com
Requires-Python: >=3.11,<4.0
Classifier: License :: Other/Proprietary License
Classifier: Programming Language :: Python :: 3
Classifier: Programming Language :: Python :: 3.11
